udrive/__init__.py
udrive/discovery.py
udrive/protocol.py
udrive/remote_object.py
udrive/serial_transport.py
udrive/shell.py
udrive/tcp_transport.py
udrive/udp_transport.py
udrive/usbbulk_transport.py
udrive/utils.py
udrive-0.1.2.dist-info/LICENSE
udrive-0.1.2.dist-info/METADATA
udrive-0.1.2.dist-info/WHEEL
udrive-0.1.2.dist-info/top_level.txt
udrive-0.1.2.dist-info/RECORD
