Metadata-Version: 2.1
Name: udrive
Version: 0.1.2
Summary: Python module for mDrive boards to control brushless motors version 0.1.2
Author: UNIT ELECTRONICS
Author-email: cesar.bautista@uelectronics.com
License: MIT License
License-File: LICENSE
Requires-Dist: appdirs ==1.4.4
Requires-Dist: blinker ==1.8.2
Requires-Dist: click ==8.1.7
Requires-Dist: colorama ==0.4.6
Requires-Dist: itsdangerous ==2.2.0
Requires-Dist: Jinja2 ==3.1.4
Requires-Dist: MarkupSafe ==2.1.5
Requires-Dist: Werkzeug ==3.0.3
